snakipy/__init__.py
snakipy/main.py
snakipy/neuro.py
snakipy/snake.py
snakipy/ui.py
snakipy-0.0.4.dist-info/entry_points.txt
snakipy-0.0.4.dist-info/LICENSE
snakipy-0.0.4.dist-info/WHEEL
snakipy-0.0.4.dist-info/METADATA
snakipy-0.0.4.dist-info/RECORD
